array_print_shape/__init__.py
array_print_shape/patch.py
array_print_shape-0.0.2.dist-info/METADATA
array_print_shape-0.0.2.dist-info/WHEEL
array_print_shape-0.0.2.dist-info/top_level.txt
array_print_shape-0.0.2.dist-info/RECORD
