Metadata-Version: 2.4
Name: array_print_shape
Version: 0.0.2
Summary: Patch torch.Tensor and numpy.ndarray to print shape.
Requires-Python: >=3.8
